AlgoToolkit/__init__.py
AlgoToolkit/algo.py
algotoolkit-2.0.0.dist-info/licenses/LICENSE
algotoolkit-2.0.0.dist-info/METADATA
algotoolkit-2.0.0.dist-info/WHEEL
algotoolkit-2.0.0.dist-info/top_level.txt
algotoolkit-2.0.0.dist-info/RECORD
