Metadata-Version: 2.4
Name: algotoolkit
Version: 2.0.0
Summary: A Python package for sorting and searching algorithms.
Author-email: Alok Kumar <alokkumarjipura9973@gmail.com>
License: Copyright (c) 2025 ALOK KUMAR
Project-URL: Homepage, https://github.com/alok1304/AlgoToolkit
Project-URL: Repository, https://github.com/alok1304/AlgoToolkit
Keywords: sorting,searching,algorithms,python,data structures
Classifier: Programming Language :: Python :: 3
Classifier: License :: OSI Approved :: MIT License
Classifier: Operating System :: OS Independent
Requires-Python: >=3.6
License-File: LICENSE
Dynamic: license-file
